Biblioteca_libros/Biblioteca_libros.py
Biblioteca_libros/__init__.py
Biblioteca_libros-0.1.dist-info/LICENSE
Biblioteca_libros-0.1.dist-info/METADATA
Biblioteca_libros-0.1.dist-info/WHEEL
Biblioteca_libros-0.1.dist-info/top_level.txt
Biblioteca_libros-0.1.dist-info/RECORD
